[
  {
    "id": "event_1755695283997_5e2hxc3ya",
    "type": "session_ended",
    "timestamp": "2025-08-20T13:08:03.997Z",
    "data": {
      "duration": 238357
    },
    "sessionId": "session_1755695045640_lm3ptig2d"
  },
  {
    "id": "event_1755695285348_62ywg2wog",
    "type": "session_started",
    "timestamp": "2025-08-20T13:08:05.348Z",
    "data": {},
    "sessionId": "session_1755695285348_y6u2x3lcs"
  },
  {
    "id": "event_1755695285475_hvxrzro18",
    "type": "session_started",
    "timestamp": "2025-08-20T13:08:05.475Z",
    "data": {
      "timestamp": "2025-08-20T13:08:05.475Z"
    },
    "sessionId": "session_1755695285348_y6u2x3lcs"
  },
  {
    "id": "event_1755695306328_96hnpcbic",
    "type": "session_ended",
    "timestamp": "2025-08-20T13:08:26.328Z",
    "data": {
      "duration": 20980
    },
    "sessionId": "session_1755695285348_y6u2x3lcs"
  },
  {
    "id": "event_1755695307104_zf002sv39",
    "type": "session_started",
    "timestamp": "2025-08-20T13:08:27.104Z",
    "data": {},
    "sessionId": "session_1755695307104_2qa76nohg"
  },
  {
    "id": "event_1755695310178_md4fd4kp0",
    "type": "session_ended",
    "timestamp": "2025-08-20T13:08:30.178Z",
    "data": {
      "duration": 3074
    },
    "sessionId": "session_1755695307104_2qa76nohg"
  },
  {
    "id": "event_1755695310711_713cxo8oo",
    "type": "session_started",
    "timestamp": "2025-08-20T13:08:30.711Z",
    "data": {},
    "sessionId": "session_1755695310711_yysuesfya"
  },
  {
    "id": "event_1755695310828_2x1rq5inm",
    "type": "session_started",
    "timestamp": "2025-08-20T13:08:30.828Z",
    "data": {
      "timestamp": "2025-08-20T13:08:30.828Z"
    },
    "sessionId": "session_1755695310711_yysuesfya"
  },
  {
    "id": "event_1755695334698_dt2y95nox",
    "type": "session_ended",
    "timestamp": "2025-08-20T13:08:54.698Z",
    "data": {
      "duration": 23987
    },
    "sessionId": "session_1755695310711_yysuesfya"
  },
  {
    "id": "event_1755695335274_87x9od0iy",
    "type": "session_started",
    "timestamp": "2025-08-20T13:08:55.274Z",
    "data": {},
    "sessionId": "session_1755695335274_ffodv3j6l"
  },
  {
    "id": "event_1755695339313_gysguhpcx",
    "type": "session_ended",
    "timestamp": "2025-08-20T13:08:59.313Z",
    "data": {
      "duration": 4039
    },
    "sessionId": "session_1755695335274_ffodv3j6l"
  },
  {
    "id": "event_1755695339883_eol16yk8g",
    "type": "session_started",
    "timestamp": "2025-08-20T13:08:59.883Z",
    "data": {},
    "sessionId": "session_1755695339883_8alw4vu0k"
  },
  {
    "id": "event_1755695344327_z7mh1yhwi",
    "type": "session_ended",
    "timestamp": "2025-08-20T13:09:04.327Z",
    "data": {
      "duration": 4444
    },
    "sessionId": "session_1755695339883_8alw4vu0k"
  },
  {
    "id": "event_1755695344867_3vjf0rvye",
    "type": "session_started",
    "timestamp": "2025-08-20T13:09:04.867Z",
    "data": {},
    "sessionId": "session_1755695344867_y6j09iblw"
  },
  {
    "id": "event_1755695350727_xmgqrz77q",
    "type": "session_ended",
    "timestamp": "2025-08-20T13:09:10.727Z",
    "data": {
      "duration": 5860
    },
    "sessionId": "session_1755695344867_y6j09iblw"
  },
  {
    "id": "event_1755695351299_lmf77hs48",
    "type": "session_started",
    "timestamp": "2025-08-20T13:09:11.299Z",
    "data": {},
    "sessionId": "session_1755695351299_4iji86f2r"
  },
  {
    "id": "event_1755695351425_1vvhr7e21",
    "type": "session_started",
    "timestamp": "2025-08-20T13:09:11.425Z",
    "data": {
      "timestamp": "2025-08-20T13:09:11.425Z"
    },
    "sessionId": "session_1755695351299_4iji86f2r"
  },
  {
    "id": "event_1755699066438_b2sjap6pm",
    "type": "session_ended",
    "timestamp": "2025-08-20T14:11:06.438Z",
    "data": {
      "duration": 3715139
    },
    "sessionId": "session_1755695351299_4iji86f2r"
  },
  {
    "id": "event_1755699068149_qn7tnlka0",
    "type": "session_started",
    "timestamp": "2025-08-20T14:11:08.149Z",
    "data": {},
    "sessionId": "session_1755699068149_uvl8f8p66"
  },
  {
    "id": "event_1755699077351_3n3dqfslo",
    "type": "session_ended",
    "timestamp": "2025-08-20T14:11:17.351Z",
    "data": {
      "duration": 9202
    },
    "sessionId": "session_1755699068149_uvl8f8p66"
  },
  {
    "id": "event_1755699077959_47i6a1623",
    "type": "session_started",
    "timestamp": "2025-08-20T14:11:17.959Z",
    "data": {},
    "sessionId": "session_1755699077959_nufif0t5j"
  },
  {
    "id": "event_1755699078079_6znydctbd",
    "type": "session_started",
    "timestamp": "2025-08-20T14:11:18.079Z",
    "data": {
      "timestamp": "2025-08-20T14:11:18.079Z"
    },
    "sessionId": "session_1755699077959_nufif0t5j"
  },
  {
    "id": "event_1755699097373_t2icoupl6",
    "type": "note_updated",
    "timestamp": "2025-08-20T14:11:37.373Z",
    "data": {
      "noteId": "sample",
      "fileName": "sample",
      "wordCount": 103,
      "characterCount": 638,
      "hasWikilinks": false,
      "tagCount": 0,
      "folder": "folder",
      "isOverwrite": false
    },
    "sessionId": "session_1755699077959_nufif0t5j"
  },
  {
    "id": "event_1755699100174_s4in9owmo",
    "type": "note_updated",
    "timestamp": "2025-08-20T14:11:40.174Z",
    "data": {
      "noteId": "sample",
      "fileName": "sample2",
      "wordCount": 103,
      "characterCount": 638,
      "hasWikilinks": false,
      "tagCount": 0,
      "folder": "folder",
      "isOverwrite": false
    },
    "sessionId": "session_1755699077959_nufif0t5j"
  },
  {
    "id": "event_1755699104739_b69xvje7x",
    "type": "note_updated",
    "timestamp": "2025-08-20T14:11:44.739Z",
    "data": {
      "noteId": "sample",
      "fileName": "sample3",
      "wordCount": 103,
      "characterCount": 638,
      "hasWikilinks": false,
      "tagCount": 0,
      "folder": "folder",
      "isOverwrite": false
    },
    "sessionId": "session_1755699077959_nufif0t5j"
  },
  {
    "id": "event_1755699151222_02qep9r74",
    "type": "note_updated",
    "timestamp": "2025-08-20T14:12:31.222Z",
    "data": {
      "noteId": "folder/sample",
      "fileName": "sample",
      "wordCount": 103,
      "characterCount": 638,
      "hasWikilinks": false,
      "tagCount": 0,
      "folder": "folder2",
      "isOverwrite": false
    },
    "sessionId": "session_1755699077959_nufif0t5j"
  },
  {
    "id": "event_1755699153869_iris6r41x",
    "type": "note_updated",
    "timestamp": "2025-08-20T14:12:33.869Z",
    "data": {
      "noteId": "folder/sample",
      "fileName": "sample1",
      "wordCount": 103,
      "characterCount": 638,
      "hasWikilinks": false,
      "tagCount": 0,
      "folder": "folder2",
      "isOverwrite": false
    },
    "sessionId": "session_1755699077959_nufif0t5j"
  },
  {
    "id": "event_1755699292425_4v0b591ej",
    "type": "session_ended",
    "timestamp": "2025-08-20T14:14:52.425Z",
    "data": {
      "duration": 214466
    },
    "sessionId": "session_1755699077959_nufif0t5j"
  },
  {
    "id": "event_1755699293700_rtdb38vpw",
    "type": "session_started",
    "timestamp": "2025-08-20T14:14:53.700Z",
    "data": {},
    "sessionId": "session_1755699293700_5ob2c75ao"
  },
  {
    "id": "event_1755699296136_omeg4ofb0",
    "type": "session_ended",
    "timestamp": "2025-08-20T14:14:56.136Z",
    "data": {
      "duration": 2436
    },
    "sessionId": "session_1755699293700_5ob2c75ao"
  },
  {
    "id": "event_1755699296649_yxcuwve6q",
    "type": "session_started",
    "timestamp": "2025-08-20T14:14:56.649Z",
    "data": {},
    "sessionId": "session_1755699296649_3ckczqae4"
  },
  {
    "id": "event_1755699299236_qwbavi4up",
    "type": "session_ended",
    "timestamp": "2025-08-20T14:14:59.236Z",
    "data": {
      "duration": 2587
    },
    "sessionId": "session_1755699296649_3ckczqae4"
  },
  {
    "id": "event_1755699299755_6cv3vzo1v",
    "type": "session_started",
    "timestamp": "2025-08-20T14:14:59.755Z",
    "data": {},
    "sessionId": "session_1755699299755_pj3vifemz"
  },
  {
    "id": "event_1755699303019_zqakhpqhc",
    "type": "session_ended",
    "timestamp": "2025-08-20T14:15:03.019Z",
    "data": {
      "duration": 3264
    },
    "sessionId": "session_1755699299755_pj3vifemz"
  },
  {
    "id": "event_1755699303591_u8b0hv87x",
    "type": "session_started",
    "timestamp": "2025-08-20T14:15:03.591Z",
    "data": {},
    "sessionId": "session_1755699303591_qxinobl20"
  },
  {
    "id": "event_1755699307469_8xg9cbi6y",
    "type": "session_ended",
    "timestamp": "2025-08-20T14:15:07.469Z",
    "data": {
      "duration": 3878
    },
    "sessionId": "session_1755699303591_qxinobl20"
  },
  {
    "id": "event_1755699307983_vzzhvmx94",
    "type": "session_started",
    "timestamp": "2025-08-20T14:15:07.983Z",
    "data": {},
    "sessionId": "session_1755699307983_ok24bgzgw"
  },
  {
    "id": "event_1755699309639_y04hvvvj7",
    "type": "session_ended",
    "timestamp": "2025-08-20T14:15:09.639Z",
    "data": {
      "duration": 1656
    },
    "sessionId": "session_1755699307983_ok24bgzgw"
  },
  {
    "id": "event_1755699310158_91lsheco7",
    "type": "session_started",
    "timestamp": "2025-08-20T14:15:10.158Z",
    "data": {},
    "sessionId": "session_1755699310158_iwmfuoinc"
  },
  {
    "id": "event_1755699310282_9fp8us6qq",
    "type": "session_started",
    "timestamp": "2025-08-20T14:15:10.282Z",
    "data": {
      "timestamp": "2025-08-20T14:15:10.282Z"
    },
    "sessionId": "session_1755699310158_iwmfuoinc"
  },
  {
    "id": "event_1755700200469_eh5euy88m",
    "type": "session_ended",
    "timestamp": "2025-08-20T14:30:00.469Z",
    "data": {
      "duration": 890310
    },
    "sessionId": "session_1755699310158_iwmfuoinc"
  },
  {
    "id": "event_1755700201822_c6fjgtef9",
    "type": "session_started",
    "timestamp": "2025-08-20T14:30:01.822Z",
    "data": {},
    "sessionId": "session_1755700201822_y1qomm64m"
  },
  {
    "id": "event_1755700201957_8iag156fa",
    "type": "session_started",
    "timestamp": "2025-08-20T14:30:01.957Z",
    "data": {
      "timestamp": "2025-08-20T14:30:01.957Z"
    },
    "sessionId": "session_1755700201822_y1qomm64m"
  }
]
