[
  {
    "id": "event_1755380117690_f0jphn4d9",
    "type": "session_ended",
    "timestamp": "2025-08-16T21:35:17.690Z",
    "data": {
      "duration": 226542
    },
    "sessionId": "session_1755379891148_n5mchm3uu"
  },
  {
    "id": "event_1755380119682_lbp6za1ij",
    "type": "session_started",
    "timestamp": "2025-08-16T21:35:19.682Z",
    "data": {},
    "sessionId": "session_1755380119682_9nhkkc026"
  },
  {
    "id": "event_1755380121665_p8krrnjg0",
    "type": "session_ended",
    "timestamp": "2025-08-16T21:35:21.665Z",
    "data": {
      "duration": 1983
    },
    "sessionId": "session_1755380119682_9nhkkc026"
  },
  {
    "id": "event_1755380122851_uq4iucwi3",
    "type": "session_started",
    "timestamp": "2025-08-16T21:35:22.851Z",
    "data": {},
    "sessionId": "session_1755380122851_b84khhhkz"
  },
  {
    "id": "event_1755380139114_ovlf58xzg",
    "type": "session_ended",
    "timestamp": "2025-08-16T21:35:39.114Z",
    "data": {
      "duration": 16263
    },
    "sessionId": "session_1755380122851_b84khhhkz"
  },
  {
    "id": "event_1755380143489_30ur3t9l4",
    "type": "session_started",
    "timestamp": "2025-08-16T21:35:43.489Z",
    "data": {},
    "sessionId": "session_1755380143489_d0ki8pq5k"
  },
  {
    "id": "event_1755380306744_9lfpce5kv",
    "type": "session_ended",
    "timestamp": "2025-08-16T21:38:26.744Z",
    "data": {
      "duration": 163255
    },
    "sessionId": "session_1755380143489_d0ki8pq5k"
  },
  {
    "id": "event_1755380308590_y9uyx8svk",
    "type": "session_started",
    "timestamp": "2025-08-16T21:38:28.590Z",
    "data": {},
    "sessionId": "session_1755380308590_xhdjlfr4a"
  },
  {
    "id": "event_1755380310618_g0a9219w7",
    "type": "session_ended",
    "timestamp": "2025-08-16T21:38:30.618Z",
    "data": {
      "duration": 2028
    },
    "sessionId": "session_1755380308590_xhdjlfr4a"
  },
  {
    "id": "event_1755380311788_3yi5u9d6i",
    "type": "session_started",
    "timestamp": "2025-08-16T21:38:31.788Z",
    "data": {},
    "sessionId": "session_1755380311788_mabdad1xu"
  },
  {
    "id": "event_1755380891334_px0w9vkc7",
    "type": "session_ended",
    "timestamp": "2025-08-16T21:48:11.334Z",
    "data": {
      "duration": 579545
    },
    "sessionId": "session_1755380311788_mabdad1xu"
  },
  {
    "id": "event_1755380893368_c6lj4j5k7",
    "type": "session_started",
    "timestamp": "2025-08-16T21:48:13.368Z",
    "data": {},
    "sessionId": "session_1755380893368_livf0hpm7"
  },
  {
    "id": "event_1755380900774_75ebpzhue",
    "type": "session_ended",
    "timestamp": "2025-08-16T21:48:20.774Z",
    "data": {
      "duration": 7406
    },
    "sessionId": "session_1755380893368_livf0hpm7"
  },
  {
    "id": "event_1755380901350_3hxwnkw4t",
    "type": "session_started",
    "timestamp": "2025-08-16T21:48:21.350Z",
    "data": {},
    "sessionId": "session_1755380901350_s3saw66kj"
  },
  {
    "id": "event_1755380901474_evpteyy7c",
    "type": "session_started",
    "timestamp": "2025-08-16T21:48:21.474Z",
    "data": {
      "timestamp": "2025-08-16T21:48:21.474Z"
    },
    "sessionId": "session_1755380901350_s3saw66kj"
  },
  {
    "id": "event_1755380910579_7y63k55u0",
    "type": "note_viewed",
    "timestamp": "2025-08-16T21:48:30.579Z",
    "data": {
      "noteId": "sample",
      "noteName": "sample.md",
      "wordCount": 84,
      "hasLinks": false,
      "tagCount": 0
    },
    "sessionId": "session_1755380901350_s3saw66kj"
  },
  {
    "id": "event_1755380921958_03vjxhemn",
    "type": "mode_switched",
    "timestamp": "2025-08-16T21:48:41.958Z",
    "data": {
      "mode": "preview"
    },
    "sessionId": "session_1755380901350_s3saw66kj"
  },
  {
    "id": "event_1755380922641_ylppuv23n",
    "type": "mode_switched",
    "timestamp": "2025-08-16T21:48:42.641Z",
    "data": {
      "mode": "split"
    },
    "sessionId": "session_1755380901350_s3saw66kj"
  },
  {
    "id": "event_1755380923526_gdqfqeo39",
    "type": "mode_switched",
    "timestamp": "2025-08-16T21:48:43.526Z",
    "data": {
      "mode": "edit"
    },
    "sessionId": "session_1755380901350_s3saw66kj"
  },
  {
    "id": "event_1755381401639_f1bcfqu6b",
    "type": "session_ended",
    "timestamp": "2025-08-16T21:56:41.639Z",
    "data": {
      "duration": 500289
    },
    "sessionId": "session_1755380901350_s3saw66kj"
  },
  {
    "id": "event_1755381403300_2g44cjy5x",
    "type": "session_started",
    "timestamp": "2025-08-16T21:56:43.300Z",
    "data": {},
    "sessionId": "session_1755381403300_otj6mwwld"
  },
  {
    "id": "event_1755381403482_bqmvn1qzg",
    "type": "session_started",
    "timestamp": "2025-08-16T21:56:43.482Z",
    "data": {
      "timestamp": "2025-08-16T21:56:43.482Z"
    },
    "sessionId": "session_1755381403300_otj6mwwld"
  },
  {
    "id": "event_1755381636641_l2ufl24dz",
    "type": "session_ended",
    "timestamp": "2025-08-16T22:00:36.641Z",
    "data": {
      "duration": 233341
    },
    "sessionId": "session_1755381403300_otj6mwwld"
  },
  {
    "id": "event_1755381638196_wuyxcy2gl",
    "type": "session_started",
    "timestamp": "2025-08-16T22:00:38.196Z",
    "data": {},
    "sessionId": "session_1755381638196_giadn0usn"
  },
  {
    "id": "event_1755381641667_liy4yz71f",
    "type": "session_ended",
    "timestamp": "2025-08-16T22:00:41.667Z",
    "data": {
      "duration": 3471
    },
    "sessionId": "session_1755381638196_giadn0usn"
  },
  {
    "id": "event_1755381642560_qcgr5wpb7",
    "type": "session_started",
    "timestamp": "2025-08-16T22:00:42.560Z",
    "data": {},
    "sessionId": "session_1755381642560_omqodnlc5"
  },
  {
    "id": "event_1755381642734_2ovv1evmv",
    "type": "session_started",
    "timestamp": "2025-08-16T22:00:42.734Z",
    "data": {
      "timestamp": "2025-08-16T22:00:42.734Z"
    },
    "sessionId": "session_1755381642560_omqodnlc5"
  },
  {
    "id": "event_1755381645972_stvqsdhmu",
    "type": "mode_switched",
    "timestamp": "2025-08-16T22:00:45.972Z",
    "data": {
      "mode": "preview"
    },
    "sessionId": "session_1755381642560_omqodnlc5"
  },
  {
    "id": "event_1755381646652_gmiolq5ww",
    "type": "mode_switched",
    "timestamp": "2025-08-16T22:00:46.652Z",
    "data": {
      "mode": "edit"
    },
    "sessionId": "session_1755381642560_omqodnlc5"
  },
  {
    "id": "event_1755381743889_vmsphflr2",
    "type": "session_ended",
    "timestamp": "2025-08-16T22:02:23.889Z",
    "data": {
      "duration": 101329
    },
    "sessionId": "session_1755381642560_omqodnlc5"
  },
  {
    "id": "event_1755381745501_ryw6v7xx1",
    "type": "session_started",
    "timestamp": "2025-08-16T22:02:25.501Z",
    "data": {},
    "sessionId": "session_1755381745501_fz51rjuxm"
  },
  {
    "id": "event_1755381747284_r2pqt94na",
    "type": "session_ended",
    "timestamp": "2025-08-16T22:02:27.284Z",
    "data": {
      "duration": 1783
    },
    "sessionId": "session_1755381745501_fz51rjuxm"
  },
  {
    "id": "event_1755381748115_964j6cqx6",
    "type": "session_started",
    "timestamp": "2025-08-16T22:02:28.115Z",
    "data": {},
    "sessionId": "session_1755381748115_3xgbm731x"
  },
  {
    "id": "event_1755381749286_y4kfeo2b4",
    "type": "session_ended",
    "timestamp": "2025-08-16T22:02:29.286Z",
    "data": {
      "duration": 1171
    },
    "sessionId": "session_1755381748115_3xgbm731x"
  },
  {
    "id": "event_1755381750145_8azhp5xr7",
    "type": "session_started",
    "timestamp": "2025-08-16T22:02:30.145Z",
    "data": {},
    "sessionId": "session_1755381750145_6yvrfx3al"
  },
  {
    "id": "event_1755381750320_do7j3ul4i",
    "type": "session_started",
    "timestamp": "2025-08-16T22:02:30.320Z",
    "data": {
      "timestamp": "2025-08-16T22:02:30.320Z"
    },
    "sessionId": "session_1755381750145_6yvrfx3al"
  },
  {
    "id": "event_1755381832241_9xyj3ynbw",
    "type": "session_ended",
    "timestamp": "2025-08-16T22:03:52.241Z",
    "data": {
      "duration": 82096
    },
    "sessionId": "session_1755381750145_6yvrfx3al"
  },
  {
    "id": "event_1755381833732_2zz94wqoy",
    "type": "session_started",
    "timestamp": "2025-08-16T22:03:53.732Z",
    "data": {},
    "sessionId": "session_1755381833732_vgy4iqb2o"
  },
  {
    "id": "event_1755381833914_zh6jglb6o",
    "type": "session_started",
    "timestamp": "2025-08-16T22:03:53.915Z",
    "data": {
      "timestamp": "2025-08-16T22:03:53.914Z"
    },
    "sessionId": "session_1755381833732_vgy4iqb2o"
  },
  {
    "id": "event_1755385313533_9qyopvt34",
    "type": "session_ended",
    "timestamp": "2025-08-16T23:01:53.533Z",
    "data": {
      "duration": 3479801
    },
    "sessionId": "session_1755381833732_vgy4iqb2o"
  },
  {
    "id": "event_1755385315148_ru88dt49e",
    "type": "session_started",
    "timestamp": "2025-08-16T23:01:55.148Z",
    "data": {},
    "sessionId": "session_1755385315148_1uj15xifh"
  },
  {
    "id": "event_1755385316369_8471s56tb",
    "type": "session_ended",
    "timestamp": "2025-08-16T23:01:56.369Z",
    "data": {
      "duration": 1221
    },
    "sessionId": "session_1755385315148_1uj15xifh"
  },
  {
    "id": "event_1755385317205_8uddca3vl",
    "type": "session_started",
    "timestamp": "2025-08-16T23:01:57.205Z",
    "data": {},
    "sessionId": "session_1755385317205_qfrl3r55x"
  },
  {
    "id": "event_1755385319902_x1ya82agi",
    "type": "session_ended",
    "timestamp": "2025-08-16T23:01:59.902Z",
    "data": {
      "duration": 2697
    },
    "sessionId": "session_1755385317205_qfrl3r55x"
  },
  {
    "id": "event_1755385320794_68qbyfh55",
    "type": "session_started",
    "timestamp": "2025-08-16T23:02:00.794Z",
    "data": {},
    "sessionId": "session_1755385320794_7jwbxmihx"
  },
  {
    "id": "event_1755385320982_nfe2u3igk",
    "type": "session_started",
    "timestamp": "2025-08-16T23:02:00.982Z",
    "data": {
      "timestamp": "2025-08-16T23:02:00.982Z"
    },
    "sessionId": "session_1755385320794_7jwbxmihx"
  },
  {
    "id": "event_1755385490647_oxtcwspqk",
    "type": "session_ended",
    "timestamp": "2025-08-16T23:04:50.647Z",
    "data": {
      "duration": 169853
    },
    "sessionId": "session_1755385320794_7jwbxmihx"
  },
  {
    "id": "event_1755385716454_r4ky66vmd",
    "type": "session_started",
    "timestamp": "2025-08-16T23:08:36.454Z",
    "data": {},
    "sessionId": "session_1755385716454_u38h16kzd"
  },
  {
    "id": "event_1755385830191_1ovrsckte",
    "type": "session_ended",
    "timestamp": "2025-08-16T23:10:30.191Z",
    "data": {
      "duration": 113737
    },
    "sessionId": "session_1755385716454_u38h16kzd"
  },
  {
    "id": "event_1755385831921_hcqcyuzvj",
    "type": "session_started",
    "timestamp": "2025-08-16T23:10:31.921Z",
    "data": {},
    "sessionId": "session_1755385831921_slq3zyogv"
  },
  {
    "id": "event_1755385833113_btpyye3eh",
    "type": "session_ended",
    "timestamp": "2025-08-16T23:10:33.113Z",
    "data": {
      "duration": 1192
    },
    "sessionId": "session_1755385831921_slq3zyogv"
  },
  {
    "id": "event_1755385839294_7njxu2dpp",
    "type": "session_started",
    "timestamp": "2025-08-16T23:10:39.294Z",
    "data": {},
    "sessionId": "session_1755385839294_hia7kq59j"
  },
  {
    "id": "event_1755385839484_o4dxx9urh",
    "type": "session_started",
    "timestamp": "2025-08-16T23:10:39.484Z",
    "data": {
      "timestamp": "2025-08-16T23:10:39.484Z"
    },
    "sessionId": "session_1755385839294_hia7kq59j"
  },
  {
    "id": "event_1755385893442_youxbj7kg",
    "type": "session_ended",
    "timestamp": "2025-08-16T23:11:33.442Z",
    "data": {
      "duration": 54148
    },
    "sessionId": "session_1755385839294_hia7kq59j"
  },
  {
    "id": "event_1755385894600_ye1h162c9",
    "type": "session_started",
    "timestamp": "2025-08-16T23:11:34.600Z",
    "data": {},
    "sessionId": "session_1755385894600_8nhzke8lq"
  },
  {
    "id": "event_1755385894793_190hp0y8u",
    "type": "session_started",
    "timestamp": "2025-08-16T23:11:34.793Z",
    "data": {
      "timestamp": "2025-08-16T23:11:34.793Z"
    },
    "sessionId": "session_1755385894600_8nhzke8lq"
  },
  {
    "id": "event_1755386039961_4sdxwzmbr",
    "type": "session_ended",
    "timestamp": "2025-08-16T23:13:59.961Z",
    "data": {
      "duration": 145361
    },
    "sessionId": "session_1755385894600_8nhzke8lq"
  },
  {
    "id": "event_1755386041405_bnoyqnpd1",
    "type": "session_started",
    "timestamp": "2025-08-16T23:14:01.405Z",
    "data": {},
    "sessionId": "session_1755386041405_i5zdzhsoh"
  },
  {
    "id": "event_1755386041592_mfnjplk2m",
    "type": "session_started",
    "timestamp": "2025-08-16T23:14:01.592Z",
    "data": {
      "timestamp": "2025-08-16T23:14:01.592Z"
    },
    "sessionId": "session_1755386041405_i5zdzhsoh"
  },
  {
    "id": "event_1755386082622_bfzdy198t",
    "type": "session_ended",
    "timestamp": "2025-08-16T23:14:42.622Z",
    "data": {
      "duration": 41217
    },
    "sessionId": "session_1755386041405_i5zdzhsoh"
  },
  {
    "id": "event_1755386083661_gnsk4a737",
    "type": "session_started",
    "timestamp": "2025-08-16T23:14:43.661Z",
    "data": {},
    "sessionId": "session_1755386083661_hambkf0pu"
  },
  {
    "id": "event_1755386083848_3k21yt32l",
    "type": "session_started",
    "timestamp": "2025-08-16T23:14:43.848Z",
    "data": {
      "timestamp": "2025-08-16T23:14:43.848Z"
    },
    "sessionId": "session_1755386083661_hambkf0pu"
  }
]
