[
  {
    "id": "event_1754755648274_ioszu16ge",
    "type": "session_ended",
    "timestamp": "2025-08-09T16:07:28.274Z",
    "data": {
      "duration": 35849
    },
    "sessionId": "session_1754755612425_c0oy8w58v"
  },
  {
    "id": "event_1754755648997_4tt2ecdfb",
    "type": "session_started",
    "timestamp": "2025-08-09T16:07:28.997Z",
    "data": {},
    "sessionId": "session_1754755648997_zryy5mh84"
  },
  {
    "id": "event_1754755649021_9k7yokt27",
    "type": "session_started",
    "timestamp": "2025-08-09T16:07:29.021Z",
    "data": {
      "timestamp": "2025-08-09T16:07:29.021Z"
    },
    "sessionId": "session_1754755648997_zryy5mh84"
  },
  {
    "id": "event_1754755651588_safblcvwa",
    "type": "ai_analysis",
    "timestamp": "2025-08-09T16:07:31.588Z",
    "data": {
      "action": "open_plugin_dashboard",
      "notesCount": 6
    },
    "sessionId": "session_1754755648997_zryy5mh84"
  },
  {
    "id": "event_1754755658205_8hm5gw3xa",
    "type": "ai_analysis",
    "timestamp": "2025-08-09T16:07:38.205Z",
    "data": {
      "action": "plugin_installed",
      "pluginId": "knowledge-graph-analytics",
      "pluginName": "Knowledge Graph Analytics"
    },
    "sessionId": "session_1754755648997_zryy5mh84"
  },
  {
    "id": "event_1754755662987_gkrasrkqj",
    "type": "ai_analysis",
    "timestamp": "2025-08-09T16:07:42.987Z",
    "data": {
      "action": "plugin_uninstalled",
      "pluginId": "smart-link-detector"
    },
    "sessionId": "session_1754755648997_zryy5mh84"
  },
  {
    "id": "event_1754755662994_5a7v4rdyj",
    "type": "ai_analysis",
    "timestamp": "2025-08-09T16:07:42.994Z",
    "data": {
      "action": "plugin_uninstalled",
      "pluginId": "smart-link-detector"
    },
    "sessionId": "session_1754755648997_zryy5mh84"
  },
  {
    "id": "event_1754755664737_bulozan9x",
    "type": "ai_analysis",
    "timestamp": "2025-08-09T16:07:44.737Z",
    "data": {
      "action": "plugin_uninstalled",
      "pluginId": "ai-writing-assistant"
    },
    "sessionId": "session_1754755648997_zryy5mh84"
  },
  {
    "id": "event_1754755664744_0iba9b5hk",
    "type": "ai_analysis",
    "timestamp": "2025-08-09T16:07:44.744Z",
    "data": {
      "action": "plugin_uninstalled",
      "pluginId": "ai-writing-assistant"
    },
    "sessionId": "session_1754755648997_zryy5mh84"
  },
  {
    "id": "event_1754756051991_agweqypa6",
    "type": "session_ended",
    "timestamp": "2025-08-09T16:14:11.991Z",
    "data": {
      "duration": 402994
    },
    "sessionId": "session_1754755648997_zryy5mh84"
  },
  {
    "id": "event_1754756053218_m83no4v7a",
    "type": "session_started",
    "timestamp": "2025-08-09T16:14:13.218Z",
    "data": {},
    "sessionId": "session_1754756053218_41j7vv1g8"
  },
  {
    "id": "event_1754756053270_y3nwlkd8q",
    "type": "session_started",
    "timestamp": "2025-08-09T16:14:13.270Z",
    "data": {
      "timestamp": "2025-08-09T16:14:13.270Z"
    },
    "sessionId": "session_1754756053218_41j7vv1g8"
  },
  {
    "id": "event_1754756054688_18iw5tbeu",
    "type": "ai_analysis",
    "timestamp": "2025-08-09T16:14:14.688Z",
    "data": {
      "action": "open_plugin_dashboard",
      "notesCount": 6
    },
    "sessionId": "session_1754756053218_41j7vv1g8"
  },
  {
    "id": "event_1754756059154_tdv5qu5u1",
    "type": "ai_analysis",
    "timestamp": "2025-08-09T16:14:19.154Z",
    "data": {
      "action": "plugin_uninstalled",
      "pluginId": "knowledge-graph-analytics"
    },
    "sessionId": "session_1754756053218_41j7vv1g8"
  },
  {
    "id": "event_1754756059166_yv7h7kb5g",
    "type": "ai_analysis",
    "timestamp": "2025-08-09T16:14:19.166Z",
    "data": {
      "action": "plugin_uninstalled",
      "pluginId": "knowledge-graph-analytics"
    },
    "sessionId": "session_1754756053218_41j7vv1g8"
  },
  {
    "id": "event_1754756063506_6rhq4yli5",
    "type": "ai_analysis",
    "timestamp": "2025-08-09T16:14:23.506Z",
    "data": {
      "action": "plugin_installed",
      "pluginId": "smart-link-detector",
      "pluginName": "Smart Link Detector"
    },
    "sessionId": "session_1754756053218_41j7vv1g8"
  },
  {
    "id": "event_1754756065238_ysdyadrca",
    "type": "ai_analysis",
    "timestamp": "2025-08-09T16:14:25.238Z",
    "data": {
      "action": "plugin_installed",
      "pluginId": "ai-writing-assistant",
      "pluginName": "AI Writing Assistant"
    },
    "sessionId": "session_1754756053218_41j7vv1g8"
  },
  {
    "id": "event_1754756069054_4jfpa2rtu",
    "type": "ai_analysis",
    "timestamp": "2025-08-09T16:14:29.054Z",
    "data": {
      "action": "plugin_uninstalled",
      "pluginId": "ai-writing-assistant"
    },
    "sessionId": "session_1754756053218_41j7vv1g8"
  },
  {
    "id": "event_1754756069066_js8p6bbsu",
    "type": "ai_analysis",
    "timestamp": "2025-08-09T16:14:29.066Z",
    "data": {
      "action": "plugin_uninstalled",
      "pluginId": "ai-writing-assistant"
    },
    "sessionId": "session_1754756053218_41j7vv1g8"
  },
  {
    "id": "event_1754756079721_qjzp0gbl6",
    "type": "ai_analysis",
    "timestamp": "2025-08-09T16:14:39.721Z",
    "data": {
      "action": "plugin_uninstalled",
      "pluginId": "smart-link-detector"
    },
    "sessionId": "session_1754756053218_41j7vv1g8"
  },
  {
    "id": "event_1754756079732_2luxmgrz1",
    "type": "ai_analysis",
    "timestamp": "2025-08-09T16:14:39.732Z",
    "data": {
      "action": "plugin_uninstalled",
      "pluginId": "smart-link-detector"
    },
    "sessionId": "session_1754756053218_41j7vv1g8"
  }
]